fsm.v
module dff ( d, clk, qn, qnbar, reset);
    input d, clk, reset;
    output reg qn, qnbar;
    always @(reset == 1) begin // resets the output to 0
        qn = 0; qnbar = 1;
    end
    always @(posedge clk) begin // positive edge triggered clock
        if(d == 0) begin
            qn = 0; qnbar = 1;
        end
        else begin
            qn = 1; qnbar = 0; 
        end
    end
endmodule

module fsm (
    input [2 : 0] q, // Takes in a 3-bit current state
    input x_in, // Takes the input
    input clk, 
    input reset,
    output [2 : 0] qn, // Returns the next state (3-bit)
    output y_out // Returns the output
);
    wire qnbar [2 : 0], dd [2 : 0];
    //Here, we assign the inputs to D-FFs in terms of the 
    //input x and the current state q :
    assign dd[2] = (q[2] & (~q[0])) | (q[1] & q[0]); 
    assign dd[1] = (q[1] & (~q[0])) | ((~q[2]) & (~q[1]) & q[0]); 
    assign dd[0] = (~q[0]) & (q[2] | q[1] | x_in); 
    //We call the 3 D-FF units as following to implement the FSM:
    dff  D1( dd[2], clk, qn[2], qnbar[2], reset);
    dff  D2( dd[1], clk, qn[1], qnbar[1], reset);
    dff  D3( dd[0], clk, qn[0], qnbar[0], reset);
    assign y_out = (~q[2]) & (~q[1]) & (q[0]);
endmodule

Sequence Generator/tb_fsm.v
module tb_fsm;
    reg [2 : 0] q;
    reg x_in;
    reg clk;
    reg reset;
    wire y_out;
    wire [2 : 0] qn;
    fsm DUT( q, x_in, clk, reset, qn, y_out);
    //initialise the device under test
    //and the clock
    always #5 clk = ~clk;
    always #40 x_in = ~x_in;
    
    initial begin
        $dumpfile("fsm.vcd");
        $dumpvars(0, tb_fsm);
        $monitor($time, " Current state = %b  Next state = %b", q, qn);
        //print the multiple states as outputs on positive clock edges
        clk <= 0;
        x_in <= 1;
        reset <= 0;
        q <= 3'b000;
        //initialise the clk, reset, and input q
        repeat(30) @(posedge clk) begin
            q <= qn;
        end
        $finish;
    end
endmodule

fsm.vcd
$date
	Wed May 19 14:12:52 2021
$end
$version
	Icarus Verilog
$end
$timescale
	1s
$end
$scope module tb_fsm $end
$var wire 1 ! y_out $end
$var wire 3 " qn [2:0] $end
$var reg 1 # clk $end
$var reg 3 $ q [2:0] $end
$var reg 1 % reset $end
$var reg 1 & x_in $end
$scope module DUT $end
$var wire 1 # clk $end
$var wire 3 ' q [2:0] $end
$var wire 1 % reset $end
$var wire 1 & x_in $end
$var wire 1 ! y_out $end
$var wire 3 ( qn [2:0] $end
$scope module D1 $end
$var wire 1 # clk $end
$var wire 1 ) d $end
$var wire 1 % reset $end
$var reg 1 * qn $end
$var reg 1 + qnbar $end
$upscope $end
$scope module D2 $end
$var wire 1 # clk $end
$var wire 1 , d $end
$var wire 1 % reset $end
$var reg 1 - qn $end
$var reg 1 . qnbar $end
$upscope $end
$scope module D3 $end
$var wire 1 # clk $end
$var wire 1 / d $end
$var wire 1 % reset $end
$var reg 1 0 qn $end
$var reg 1 1 qnbar $end
$upscope $end
$upscope $end
$upscope $end
$enddefinitions $end
#0
$dumpvars
11
00
1/
1.
0-
0,
1+
0*
0)
b0 (
b0 '
1&
0%
b0 $
0#
b0 "
0!
$end
#5
01
b1 "
b1 (
10
1#
#10
0#
#15
1,
0/
1!
b1 $
b1 '
1#
#20
0#
#25
0.
1-
11
b10 "
b10 (
00
1#
#30
0#
#35
1/
0!
b10 $
b10 '
1#
#40
0#
0&
#45
01
b11 "
b11 (
10
1#
#50
0#
#55
0,
1)
0/
b11 $
b11 '
1#
#60
0#
#65
0+
1*
1.
0-
11
b100 "
b100 (
00
1#
#70
0#
#75
1/
b100 $
b100 '
1#
#80
0#
1&
#85
01
b101 "
b101 (
10
1#
#90
0#
#95
0)
0/
b101 $
b101 '
1#
#100
0#
#105
1+
0*
11
b0 "
b0 (
00
1#
#110
0#
#115
1/
b0 $
b0 '
1#
#120
0/
0#
0&
#125
1#
#130
0#
#135
1#
#140
0#
#145
1#
#150
0#
#155
1#
#160
1/
0#
1&
#165
01
b1 "
b1 (
10
1#
#170
0#
#175
1,
0/
1!
b1 $
b1 '
1#
#180
0#
#185
0.
1-
11
b10 "
b10 (
00
1#
#190
0#
#195
1/
0!
b10 $
b10 '
1#
#200
0#
0&
#205
01
b11 "
b11 (
10
1#
#210
0#
#215
0,
1)
0/
b11 $
b11 '
1#
#220
0#
#225
0+
1*
1.
0-
11
b100 "
b100 (
00
1#
#230
0#
#235
1/
b100 $
b100 '
1#
#240
0#
1&
#245
01
b101 "
b101 (
10
1#
#250
0#
#255
0)
0/
b101 $
b101 '
1#
#260
0#
#265
1+
0*
11
b0 "
b0 (
00
1#
#270
0#
#275
1/
b0 $
b0 '
1#
#280
0/
0#
0&
