grayctr.v
module srff ( q, qbar, qcur, s, r, clk, reset);
    input s, r, clk, qcur, reset;
    output reg q, qbar;
    always @(reset == 1) begin  // resets the output to 0
        q = 0; qbar = 1;
    end
    always @(posedge clk) begin //positive edge triggered clock
        if(s == 1 & r == 0) begin
            q = 1; qbar = 0;
        end
        else if (s == 0 & r == 1) begin
            q = 0; qbar = 1;
        end
        else if (s == 0 & r == 0) begin
            q = qcur; qbar = ~qcur;
        end
    end
endmodule

module grayctr (
    input [3 : 0] q,   //Takes in the 4-bit current state
    input clk,
    input reset,
    output [3 : 0] qn   //Counter outputs the next state 
);
    wire qdash[0 : 3], s[0 : 3], r[0 : 3];
    //Now we assign the inputs to SR-FFs in terms of the input q.
    assign s[3] = q[2] & (~q[1]) & (~q[0]);
    assign r[3] = (~q[2]) & (~q[1]) & (~q[0]);
    assign s[2] = (~q[3]) & q[1] & (~q[0]);
    assign r[2] = q[3] & q[1] & (~q[0]);
    assign s[1] = q[0] & (~(q[2] ^ q[3]));
    assign r[1] = q[0] & (q[2] ^ q[3]);
    assign s[0] = (~(q[3] ^ q[2] ^ q[1]));
    assign r[0] = (q[3] ^ q[2] ^ q[1]);
    //To implement the gray code counter, we call 4 SR-FF units as follows :
    srff FF1(qn[3], qdash[3], q[3], s[3], r[3], clk, reset);
    srff FF2(qn[2], qdash[2], q[2], s[2], r[2], clk, reset);
    srff FF3(qn[1], qdash[1], q[1], s[1], r[1], clk, reset);
    srff FF4(qn[0], qdash[0], q[0], s[0], r[0], clk, reset);
endmodule

tb_grayctr.v
module tb_grayctr;
    reg [3 : 0] q;
    reg clk;
    reg reset;
    wire [3 : 0] qn;
    grayctr DUT( q, clk, reset, qn); // initialise the device under test
    always #5 clk = ~clk;            // and the clock

    initial begin
        $dumpfile("grayctr.vcd");
        $dumpvars(0, tb_grayctr);
        $monitor($time, " Current state = %b  Next state = %b", q, qn);
        clk <= 0;
        reset <=0;
        q <= 4'b0000;
        repeat(1) @(posedge clk) begin //reset the input and the output
            reset <=0;
        end
        repeat(31) @(posedge clk) begin //executes a full cycle of the counter
            q <= qn;
        end
        $finish;
    end
endmodule

Gray-Code/grayctr.vcd
$date
	Tue May 18 12:38:19 2021
$end
$version
	Icarus Verilog
$end
$timescale
	1s
$end
$scope module tb_grayctr $end
$var wire 4 ! qn [3:0] $end
$var reg 1 " clk $end
$var reg 4 # q [3:0] $end
$var reg 1 $ reset $end
$scope module DUT $end
$var wire 1 " clk $end
$var wire 4 % q [3:0] $end
$var wire 1 $ reset $end
$var wire 4 & qn [3:0] $end
$scope module FF1 $end
$var wire 1 " clk $end
$var wire 1 ' qcur $end
$var wire 1 ( r $end
$var wire 1 $ reset $end
$var wire 1 ) s $end
$var reg 1 * q $end
$var reg 1 + qbar $end
$upscope $end
$scope module FF2 $end
$var wire 1 " clk $end
$var wire 1 , qcur $end
$var wire 1 - r $end
$var wire 1 $ reset $end
$var wire 1 . s $end
$var reg 1 / q $end
$var reg 1 0 qbar $end
$upscope $end
$scope module FF3 $end
$var wire 1 " clk $end
$var wire 1 1 qcur $end
$var wire 1 2 r $end
$var wire 1 $ reset $end
$var wire 1 3 s $end
$var reg 1 4 q $end
$var reg 1 5 qbar $end
$upscope $end
$scope module FF4 $end
$var wire 1 " clk $end
$var wire 1 6 qcur $end
$var wire 1 7 r $end
$var wire 1 $ reset $end
$var wire 1 8 s $end
$var reg 1 9 q $end
$var reg 1 : qbar $end
$upscope $end
$upscope $end
$upscope $end
$enddefinitions $end
#0
$dumpvars
1:
09
18
07
06
15
04
03
02
01
10
0/
0.
0-
0,
1+
0*
0)
1(
0'
b0 &
b0 %
0$
b0 #
0"
b0 !
$end
#5
0:
b1 !
b1 &
19
1"
#10
0"
#15
0(
13
16
b1 #
b1 %
1"
#20
0"
#25
05
b11 !
b11 &
14
1"
#30
0"
#35
08
17
11
b11 #
b11 %
1"
#40
0"
#45
1:
b10 !
b10 &
09
1"
#50
0"
#55
1.
03
06
b10 #
b10 %
1"
#60
0"
#65
00
b110 !
b110 &
1/
1"
#70
0"
#75
18
07
1,
b110 #
b110 %
1"
#80
0"
#85
0:
b111 !
b111 &
19
1"
#90
0"
#95
0.
12
16
b111 #
b111 %
1"
#100
0"
#105
15
b101 !
b101 &
04
1"
#110
0"
#115
08
17
01
b101 #
b101 %
1"
#120
0"
#125
1:
b100 !
b100 &
09
1"
#130
0"
#135
1)
02
06
b100 #
b100 %
1"
#140
0"
#145
0+
b1100 !
b1100 &
1*
1"
#150
0"
#155
18
07
1'
b1100 #
b1100 %
1"
#160
0"
#165
0:
b1101 !
b1101 &
19
1"
#170
0"
#175
0)
13
16
b1101 #
b1101 %
1"
#180
0"
#185
05
b1111 !
b1111 &
14
1"
#190
0"
#195
08
17
11
b1111 #
b1111 %
1"
#200
0"
#205
1:
b1110 !
b1110 &
09
1"
#210
0"
#215
1-
03
06
b1110 #
b1110 %
1"
#220
0"
#225
10
b1010 !
b1010 &
0/
1"
#230
0"
#235
18
07
0,
b1010 #
b1010 %
1"
#240
0"
#245
0:
b1011 !
b1011 &
19
1"
#250
0"
#255
0-
12
16
b1011 #
b1011 %
1"
#260
0"
#265
15
b1001 !
b1001 &
04
1"
#270
0"
#275
08
17
01
b1001 #
b1001 %
1"
#280
0"
#285
1:
b1000 !
b1000 &
09
1"
#290
0"
#295
1(
02
06
b1000 #
b1000 %
1"
#300
0"
#305
1+
b0 !
b0 &
0*
1"
#310
0"
#315
18
07
0'
b0 #
b0 %
1"
